cvpkgs_IGNchinmay/__init__.py
cvpkgs_IGNchinmay/json_utils.py
cvpkgs1_IGNchinmay-0.0.1.dist-info/LICENSE.txt
cvpkgs1_IGNchinmay-0.0.1.dist-info/METADATA
cvpkgs1_IGNchinmay-0.0.1.dist-info/WHEEL
cvpkgs1_IGNchinmay-0.0.1.dist-info/top_level.txt
cvpkgs1_IGNchinmay-0.0.1.dist-info/RECORD
