Metadata-Version: 2.1
Name: cvpkgs1_IGNchinmay
Version: 0.0.1
Summary: A small CV test package
Author-email: Chinmay <chinmayananda.sahu@ignitarium.com>
Project-URL: Homepage, https://gitlab.ignitarium.in/chinmayananda_sahu/cvutils
Project-URL: Issues, https://gitlab.ignitarium.in/chinmayananda_sahu/cvutils/-/issues
Classifier: Programming Language :: Python :: 3
Classifier: License :: OSI Approved :: MIT License
Classifier: Operating System :: OS Independent
Requires-Python: >=3.8
License-File: LICENSE.txt
Requires-Dist: docker
Requires-Dist: easyprocess
Requires-Dist: fabulous
Requires-Dist: imgaug
Requires-Dist: loguru
Requires-Dist: lsb-release-ex
Requires-Dist: matplotlib
Requires-Dist: numpy ==1.23.0
Requires-Dist: opencv-python
Requires-Dist: pandas
Requires-Dist: Pillow
Requires-Dist: pynput
Requires-Dist: scikit-image
Requires-Dist: shapely
Requires-Dist: sympy
Requires-Dist: termcolor
